{
  "analysis_metadata": {
    "analysis_id": "madrid_sub-036_run-01_seizure_01_20250623_172257",
    "timestamp": "2025-06-23T17:22:57.341293Z",
    "madrid_version": "1.0.0",
    "analysis_type": "single_file",
    "computation_info": {
      "execution_time_seconds": 120.22914838790894,
      "gpu_used": true,
      "memory_peak_mb": 0,
      "analysis_successful": true
    },
    "tolerance_applied": {
      "pre_seizure_minutes": 5.0,
      "post_seizure_minutes": 3.0,
      "pre_seizure_samples": 2400,
      "post_seizure_samples": 1440,
      "reprocessed_timestamp": "2025-07-01"
    }
  },
  "input_data": {
    "source_file": "/home/swolf/asim_shared/preprocessed_data/seizure_only/8hz_30min/downsample_8hz_context_30min/sub-036_run-01_seizure_01_preprocessed.pkl",
    "subject_id": "sub-036",
    "run_id": "run-01",
    "seizure_id": "seizure_01",
    "signal_metadata": {
      "sampling_rate": 8,
      "original_sampling_rate": 250,
      "signal_length_samples": 29128,
      "signal_duration_seconds": 3641.0,
      "preprocessing_info": {
        "method": "seizure_only",
        "context_minutes": 30,
        "filter_applied": {
          "low_freq": 0.5,
          "high_freq": 40,
          "order": 4
        },
        "downsampling_factor": 31.25
      }
    }
  },
  "madrid_parameters": {
    "m_range": {
      "min_length": 80,
      "max_length": 800,
      "step_size": 80
    },
    "analysis_config": {
      "top_k": 5,
      "train_test_split_ratio": 0.3,
      "threshold_percentile": 90
    },
    "algorithm_settings": {
      "use_gpu": true,
      "downsampling_factor": 1
    }
  },
  "analysis_results": {
    "anomalies": [
      {
        "rank": 1,
        "m_value": 480,
        "anomaly_score": 0.6327166305401741,
        "location_sample": 10594,
        "location_time_seconds": 1324.25,
        "seizure_hit": false,
        "normalized_score": 0.6327166305401741,
        "confidence": 0.6327166305401741,
        "anomaly_id": "m480_rank1_loc10594"
      },
      {
        "rank": 2,
        "m_value": 800,
        "anomaly_score": 0.6309573962201601,
        "location_sample": 8887,
        "location_time_seconds": 1110.875,
        "seizure_hit": false,
        "normalized_score": 0.6309573962201601,
        "confidence": 0.6309573962201601,
        "anomaly_id": "m800_rank2_loc8887"
      },
      {
        "rank": 3,
        "m_value": 400,
        "anomaly_score": 0.6279480184163311,
        "location_sample": 10594,
        "location_time_seconds": 1324.25,
        "seizure_hit": false,
        "normalized_score": 0.6279480184163311,
        "confidence": 0.6279480184163311,
        "anomaly_id": "m400_rank3_loc10594"
      },
      {
        "rank": 4,
        "m_value": 720,
        "anomaly_score": 0.6278736562519822,
        "location_sample": 8964,
        "location_time_seconds": 1120.5,
        "seizure_hit": false,
        "normalized_score": 0.6278736562519822,
        "confidence": 0.6278736562519822,
        "anomaly_id": "m720_rank4_loc8964"
      },
      {
        "rank": 5,
        "m_value": 400,
        "anomaly_score": 0.6261802169878259,
        "location_sample": 25967,
        "location_time_seconds": 3245.875,
        "seizure_hit": false,
        "normalized_score": 0.6261802169878259,
        "confidence": 0.6261802169878259,
        "anomaly_id": "m400_rank5_loc25967"
      },
      {
        "rank": 6,
        "m_value": 480,
        "anomaly_score": 0.6253076042493866,
        "location_sample": 25935,
        "location_time_seconds": 3241.875,
        "seizure_hit": false,
        "normalized_score": 0.6253076042493866,
        "confidence": 0.6253076042493866,
        "anomaly_id": "m480_rank6_loc25935"
      },
      {
        "rank": 7,
        "m_value": 640,
        "anomaly_score": 0.6239333741192074,
        "location_sample": 9047,
        "location_time_seconds": 1130.875,
        "seizure_hit": false,
        "normalized_score": 0.6239333741192074,
        "confidence": 0.6239333741192074,
        "anomaly_id": "m640_rank7_loc9047"
      },
      {
        "rank": 8,
        "m_value": 800,
        "anomaly_score": 0.6238114124912917,
        "location_sample": 9530,
        "location_time_seconds": 1191.25,
        "seizure_hit": false,
        "normalized_score": 0.6238114124912917,
        "confidence": 0.6238114124912917,
        "anomaly_id": "m800_rank8_loc9530"
      },
      {
        "rank": 9,
        "m_value": 320,
        "anomaly_score": 0.6224370168767619,
        "location_sample": 10594,
        "location_time_seconds": 1324.25,
        "seizure_hit": false,
        "normalized_score": 0.6224370168767619,
        "confidence": 0.6224370168767619,
        "anomaly_id": "m320_rank9_loc10594"
      },
      {
        "rank": 10,
        "m_value": 320,
        "anomaly_score": 0.6224180798303579,
        "location_sample": 25909,
        "location_time_seconds": 3238.625,
        "seizure_hit": false,
        "normalized_score": 0.6224180798303579,
        "confidence": 0.6224180798303579,
        "anomaly_id": "m320_rank10_loc25909"
      },
      {
        "rank": 11,
        "m_value": 800,
        "anomaly_score": 0.6218303697484775,
        "location_sample": 9090,
        "location_time_seconds": 1136.25,
        "seizure_hit": false,
        "normalized_score": 0.6218303697484775,
        "confidence": 0.6218303697484775,
        "anomaly_id": "m800_rank11_loc9090"
      },
      {
        "rank": 12,
        "m_value": 720,
        "anomaly_score": 0.6215945131510293,
        "location_sample": 9688,
        "location_time_seconds": 1211.0,
        "seizure_hit": false,
        "normalized_score": 0.6215945131510293,
        "confidence": 0.6215945131510293,
        "anomaly_id": "m720_rank12_loc9688"
      },
      {
        "rank": 13,
        "m_value": 240,
        "anomaly_score": 0.6209763852872668,
        "location_sample": 10690,
        "location_time_seconds": 1336.25,
        "seizure_hit": false,
        "normalized_score": 0.6209763852872668,
        "confidence": 0.6209763852872668,
        "anomaly_id": "m240_rank13_loc10690"
      },
      {
        "rank": 14,
        "m_value": 240,
        "anomaly_score": 0.6209734206341417,
        "location_sample": 25963,
        "location_time_seconds": 3245.375,
        "seizure_hit": false,
        "normalized_score": 0.6209734206341417,
        "confidence": 0.6209734206341417,
        "anomaly_id": "m240_rank14_loc25963"
      },
      {
        "rank": 15,
        "m_value": 240,
        "anomaly_score": 0.6209573431491527,
        "location_sample": 26031,
        "location_time_seconds": 3253.875,
        "seizure_hit": false,
        "normalized_score": 0.6209573431491527,
        "confidence": 0.6209573431491527,
        "anomaly_id": "m240_rank15_loc26031"
      },
      {
        "rank": 16,
        "m_value": 800,
        "anomaly_score": 0.6205617207318109,
        "location_sample": 9299,
        "location_time_seconds": 1162.375,
        "seizure_hit": false,
        "normalized_score": 0.6205617207318109,
        "confidence": 0.6205617207318109,
        "anomaly_id": "m800_rank16_loc9299"
      },
      {
        "rank": 17,
        "m_value": 720,
        "anomaly_score": 0.620214957624565,
        "location_sample": 9400,
        "location_time_seconds": 1175.0,
        "seizure_hit": false,
        "normalized_score": 0.620214957624565,
        "confidence": 0.620214957624565,
        "anomaly_id": "m720_rank17_loc9400"
      },
      {
        "rank": 18,
        "m_value": 720,
        "anomaly_score": 0.6195853799086677,
        "location_sample": 9147,
        "location_time_seconds": 1143.375,
        "seizure_hit": false,
        "normalized_score": 0.6195853799086677,
        "confidence": 0.6195853799086677,
        "anomaly_id": "m720_rank18_loc9147"
      },
      {
        "rank": 19,
        "m_value": 560,
        "anomaly_score": 0.6195182592352775,
        "location_sample": 9127,
        "location_time_seconds": 1140.875,
        "seizure_hit": false,
        "normalized_score": 0.6195182592352775,
        "confidence": 0.6195182592352775,
        "anomaly_id": "m560_rank19_loc9127"
      },
      {
        "rank": 20,
        "m_value": 640,
        "anomaly_score": 0.6192323751852066,
        "location_sample": 9688,
        "location_time_seconds": 1211.0,
        "seizure_hit": false,
        "normalized_score": 0.6192323751852066,
        "confidence": 0.6192323751852066,
        "anomaly_id": "m640_rank20_loc9688"
      },
      {
        "rank": 21,
        "m_value": 560,
        "anomaly_score": 0.6187854183221205,
        "location_sample": 10595,
        "location_time_seconds": 1324.375,
        "seizure_hit": false,
        "normalized_score": 0.6187854183221205,
        "confidence": 0.6187854183221205,
        "anomaly_id": "m560_rank21_loc10595"
      },
      {
        "rank": 22,
        "m_value": 640,
        "anomaly_score": 0.6186066125698344,
        "location_sample": 9528,
        "location_time_seconds": 1191.0,
        "seizure_hit": false,
        "normalized_score": 0.6186066125698344,
        "confidence": 0.6186066125698344,
        "anomaly_id": "m640_rank22_loc9528"
      },
      {
        "rank": 23,
        "m_value": 320,
        "anomaly_score": 0.6185900477571312,
        "location_sample": 26015,
        "location_time_seconds": 3251.875,
        "seizure_hit": false,
        "normalized_score": 0.6185900477571312,
        "confidence": 0.6185900477571312,
        "anomaly_id": "m320_rank23_loc26015"
      },
      {
        "rank": 24,
        "m_value": 240,
        "anomaly_score": 0.6178789755605631,
        "location_sample": 10594,
        "location_time_seconds": 1324.25,
        "seizure_hit": false,
        "normalized_score": 0.6178789755605631,
        "confidence": 0.6178789755605631,
        "anomaly_id": "m240_rank24_loc10594"
      },
      {
        "rank": 25,
        "m_value": 480,
        "anomaly_score": 0.6172191415810903,
        "location_sample": 9206,
        "location_time_seconds": 1150.75,
        "seizure_hit": false,
        "normalized_score": 0.6172191415810903,
        "confidence": 0.6172191415810903,
        "anomaly_id": "m480_rank25_loc9206"
      },
      {
        "rank": 26,
        "m_value": 560,
        "anomaly_score": 0.6168848978852868,
        "location_sample": 9688,
        "location_time_seconds": 1211.0,
        "seizure_hit": false,
        "normalized_score": 0.6168848978852868,
        "confidence": 0.6168848978852868,
        "anomaly_id": "m560_rank26_loc9688"
      },
      {
        "rank": 27,
        "m_value": 640,
        "anomaly_score": 0.6160494512452003,
        "location_sample": 9210,
        "location_time_seconds": 1151.25,
        "seizure_hit": false,
        "normalized_score": 0.6160494512452003,
        "confidence": 0.6160494512452003,
        "anomaly_id": "m640_rank27_loc9210"
      },
      {
        "rank": 28,
        "m_value": 400,
        "anomaly_score": 0.6156714331408795,
        "location_sample": 25837,
        "location_time_seconds": 3229.625,
        "seizure_hit": false,
        "normalized_score": 0.6156714331408795,
        "confidence": 0.6156714331408795,
        "anomaly_id": "m400_rank28_loc25837"
      },
      {
        "rank": 29,
        "m_value": 560,
        "anomaly_score": 0.6154087581163186,
        "location_sample": 9530,
        "location_time_seconds": 1191.25,
        "seizure_hit": false,
        "normalized_score": 0.6154087581163186,
        "confidence": 0.6154087581163186,
        "anomaly_id": "m560_rank29_loc9530"
      },
      {
        "rank": 30,
        "m_value": 480,
        "anomaly_score": 0.6148921314879011,
        "location_sample": 9688,
        "location_time_seconds": 1211.0,
        "seizure_hit": false,
        "normalized_score": 0.6148921314879011,
        "confidence": 0.6148921314879011,
        "anomaly_id": "m480_rank30_loc9688"
      },
      {
        "rank": 31,
        "m_value": 560,
        "anomaly_score": 0.6139891814355237,
        "location_sample": 9390,
        "location_time_seconds": 1173.75,
        "seizure_hit": false,
        "normalized_score": 0.6139891814355237,
        "confidence": 0.6139891814355237,
        "anomaly_id": "m560_rank31_loc9390"
      },
      {
        "rank": 32,
        "m_value": 160,
        "anomaly_score": 0.6136440451309837,
        "location_sample": 10720,
        "location_time_seconds": 1340.0,
        "seizure_hit": false,
        "normalized_score": 0.6136440451309837,
        "confidence": 0.6136440451309837,
        "anomaly_id": "m160_rank32_loc10720"
      },
      {
        "rank": 33,
        "m_value": 400,
        "anomaly_score": 0.6128825705033027,
        "location_sample": 9285,
        "location_time_seconds": 1160.625,
        "seizure_hit": false,
        "normalized_score": 0.6128825705033027,
        "confidence": 0.6128825705033027,
        "anomaly_id": "m400_rank33_loc9285"
      },
      {
        "rank": 34,
        "m_value": 160,
        "anomaly_score": 0.6128474017532859,
        "location_sample": 26044,
        "location_time_seconds": 3255.5,
        "seizure_hit": false,
        "normalized_score": 0.6128474017532859,
        "confidence": 0.6128474017532859,
        "anomaly_id": "m160_rank34_loc26044"
      },
      {
        "rank": 35,
        "m_value": 480,
        "anomaly_score": 0.6127903310218895,
        "location_sample": 16610,
        "location_time_seconds": 2076.25,
        "seizure_hit": false,
        "normalized_score": 0.6127903310218895,
        "confidence": 0.6127903310218895,
        "anomaly_id": "m480_rank35_loc16610"
      },
      {
        "rank": 36,
        "m_value": 800,
        "anomaly_score": 0.6123389032509291,
        "location_sample": 10583,
        "location_time_seconds": 1322.875,
        "seizure_hit": false,
        "normalized_score": 0.6123389032509291,
        "confidence": 0.6123389032509291,
        "anomaly_id": "m800_rank36_loc10583"
      },
      {
        "rank": 37,
        "m_value": 400,
        "anomaly_score": 0.6118660425586153,
        "location_sample": 9688,
        "location_time_seconds": 1211.0,
        "seizure_hit": false,
        "normalized_score": 0.6118660425586153,
        "confidence": 0.6118660425586153,
        "anomaly_id": "m400_rank37_loc9688"
      },
      {
        "rank": 38,
        "m_value": 160,
        "anomaly_score": 0.6117372266018246,
        "location_sample": 25988,
        "location_time_seconds": 3248.5,
        "seizure_hit": false,
        "normalized_score": 0.6117372266018246,
        "confidence": 0.6117372266018246,
        "anomaly_id": "m160_rank38_loc25988"
      },
      {
        "rank": 39,
        "m_value": 320,
        "anomaly_score": 0.6112728408928397,
        "location_sample": 10684,
        "location_time_seconds": 1335.5,
        "seizure_hit": false,
        "normalized_score": 0.6112728408928397,
        "confidence": 0.6112728408928397,
        "anomaly_id": "m320_rank39_loc10684"
      },
      {
        "rank": 40,
        "m_value": 720,
        "anomaly_score": 0.609389801007297,
        "location_sample": 10582,
        "location_time_seconds": 1322.75,
        "seizure_hit": false,
        "normalized_score": 0.609389801007297,
        "confidence": 0.609389801007297,
        "anomaly_id": "m720_rank40_loc10582"
      },
      {
        "rank": 41,
        "m_value": 320,
        "anomaly_score": 0.6087239017236707,
        "location_sample": 9688,
        "location_time_seconds": 1211.0,
        "seizure_hit": false,
        "normalized_score": 0.6087239017236707,
        "confidence": 0.6087239017236707,
        "anomaly_id": "m320_rank41_loc9688"
      },
      {
        "rank": 42,
        "m_value": 160,
        "anomaly_score": 0.6049240563270837,
        "location_sample": 10594,
        "location_time_seconds": 1324.25,
        "seizure_hit": false,
        "normalized_score": 0.6049240563270837,
        "confidence": 0.6049240563270837,
        "anomaly_id": "m160_rank42_loc10594"
      },
      {
        "rank": 43,
        "m_value": 240,
        "anomaly_score": 0.6038497313694361,
        "location_sample": 9688,
        "location_time_seconds": 1211.0,
        "seizure_hit": false,
        "normalized_score": 0.6038497313694361,
        "confidence": 0.6038497313694361,
        "anomaly_id": "m240_rank43_loc9688"
      },
      {
        "rank": 44,
        "m_value": 160,
        "anomaly_score": 0.6015634954672981,
        "location_sample": 10775,
        "location_time_seconds": 1346.875,
        "seizure_hit": false,
        "normalized_score": 0.6015634954672981,
        "confidence": 0.6015634954672981,
        "anomaly_id": "m160_rank44_loc10775"
      },
      {
        "rank": 45,
        "m_value": 80,
        "anomaly_score": 0.596852731127935,
        "location_sample": 10782,
        "location_time_seconds": 1347.75,
        "seizure_hit": false,
        "normalized_score": 0.596852731127935,
        "confidence": 0.596852731127935,
        "anomaly_id": "m80_rank45_loc10782"
      },
      {
        "rank": 46,
        "m_value": 640,
        "anomaly_score": 0.5965525590282568,
        "location_sample": 10595,
        "location_time_seconds": 1324.375,
        "seizure_hit": false,
        "normalized_score": 0.5965525590282568,
        "confidence": 0.5965525590282568,
        "anomaly_id": "m640_rank46_loc10595"
      },
      {
        "rank": 47,
        "m_value": 80,
        "anomaly_score": 0.5959906145317012,
        "location_sample": 26052,
        "location_time_seconds": 3256.5,
        "seizure_hit": false,
        "normalized_score": 0.5959906145317012,
        "confidence": 0.5959906145317012,
        "anomaly_id": "m80_rank47_loc26052"
      },
      {
        "rank": 48,
        "m_value": 80,
        "anomaly_score": 0.5944705199644894,
        "location_sample": 19684,
        "location_time_seconds": 2460.5,
        "seizure_hit": false,
        "normalized_score": 0.5944705199644894,
        "confidence": 0.5944705199644894,
        "anomaly_id": "m80_rank48_loc19684"
      },
      {
        "rank": 49,
        "m_value": 80,
        "anomaly_score": 0.594135249957983,
        "location_sample": 22785,
        "location_time_seconds": 2848.125,
        "seizure_hit": false,
        "normalized_score": 0.594135249957983,
        "confidence": 0.594135249957983,
        "anomaly_id": "m80_rank49_loc22785"
      },
      {
        "rank": 50,
        "m_value": 80,
        "anomaly_score": 0.5933689076668853,
        "location_sample": 18444,
        "location_time_seconds": 2305.5,
        "seizure_hit": false,
        "normalized_score": 0.5933689076668853,
        "confidence": 0.5933689076668853,
        "anomaly_id": "m80_rank50_loc18444"
      }
    ],
    "performance_metrics": {
      "total_anomalies_detected": 50,
      "threshold_used": 0.5820955453886475,
      "analysis_successful": true,
      "true_positives": 0,
      "false_positives": 50,
      "sensitivity": 0.0,
      "precision": 0.0
    },
    "multi_length_matrix": {
      "description": "Multi-length discord table with normalized scores",
      "shape": [
        10,
        29128
      ],
      "m_values": [
        80,
        160,
        240,
        320,
        400,
        480,
        560,
        640,
        720,
        800
      ],
      "statistics": {
        "max_score": 0.6327166305401741,
        "min_score": 0.596852731127935,
        "mean_score": 0.6216857513206079,
        "std_score": 0.009885925413120257
      }
    }
  },
  "validation_data": {
    "ground_truth": {
      "seizure_present": true,
      "seizure_regions": [
        {
          "onset_sample": 14400,
          "offset_sample": 14728,
          "onset_time_seconds": 1800.0,
          "offset_time_seconds": 1841.0,
          "duration_seconds": 41.0,
          "seizure_type": "focal",
          "confidence": 1.0
        }
      ],
      "annotation_source": "seizure_only_preprocessing",
      "annotator_id": "automated"
    },
    "seizure_overlap_info": [
      {
        "anomaly_id": "m480_rank1_loc10594",
        "overlap_with_seizure": false,
        "overlap_sample_start": null,
        "overlap_sample_end": null,
        "overlap_ratio": 0.0,
        "distance_to_onset": null,
        "classification": "false_positive"
      },
      {
        "anomaly_id": "m800_rank2_loc8887",
        "overlap_with_seizure": false,
        "overlap_sample_start": null,
        "overlap_sample_end": null,
        "overlap_ratio": 0.0,
        "distance_to_onset": null,
        "classification": "false_positive"
      },
      {
        "anomaly_id": "m400_rank3_loc10594",
        "overlap_with_seizure": false,
        "overlap_sample_start": null,
        "overlap_sample_end": null,
        "overlap_ratio": 0.0,
        "distance_to_onset": null,
        "classification": "false_positive"
      },
      {
        "anomaly_id": "m720_rank4_loc8964",
        "overlap_with_seizure": false,
        "overlap_sample_start": null,
        "overlap_sample_end": null,
        "overlap_ratio": 0.0,
        "distance_to_onset": null,
        "classification": "false_positive"
      },
      {
        "anomaly_id": "m400_rank5_loc25967",
        "overlap_with_seizure": false,
        "overlap_sample_start": null,
        "overlap_sample_end": null,
        "overlap_ratio": 0.0,
        "distance_to_onset": null,
        "classification": "false_positive"
      },
      {
        "anomaly_id": "m480_rank6_loc25935",
        "overlap_with_seizure": false,
        "overlap_sample_start": null,
        "overlap_sample_end": null,
        "overlap_ratio": 0.0,
        "distance_to_onset": null,
        "classification": "false_positive"
      },
      {
        "anomaly_id": "m640_rank7_loc9047",
        "overlap_with_seizure": false,
        "overlap_sample_start": null,
        "overlap_sample_end": null,
        "overlap_ratio": 0.0,
        "distance_to_onset": null,
        "classification": "false_positive"
      },
      {
        "anomaly_id": "m800_rank8_loc9530",
        "overlap_with_seizure": false,
        "overlap_sample_start": null,
        "overlap_sample_end": null,
        "overlap_ratio": 0.0,
        "distance_to_onset": null,
        "classification": "false_positive"
      },
      {
        "anomaly_id": "m320_rank9_loc10594",
        "overlap_with_seizure": false,
        "overlap_sample_start": null,
        "overlap_sample_end": null,
        "overlap_ratio": 0.0,
        "distance_to_onset": null,
        "classification": "false_positive"
      },
      {
        "anomaly_id": "m320_rank10_loc25909",
        "overlap_with_seizure": false,
        "overlap_sample_start": null,
        "overlap_sample_end": null,
        "overlap_ratio": 0.0,
        "distance_to_onset": null,
        "classification": "false_positive"
      },
      {
        "anomaly_id": "m800_rank11_loc9090",
        "overlap_with_seizure": false,
        "overlap_sample_start": null,
        "overlap_sample_end": null,
        "overlap_ratio": 0.0,
        "distance_to_onset": null,
        "classification": "false_positive"
      },
      {
        "anomaly_id": "m720_rank12_loc9688",
        "overlap_with_seizure": false,
        "overlap_sample_start": null,
        "overlap_sample_end": null,
        "overlap_ratio": 0.0,
        "distance_to_onset": null,
        "classification": "false_positive"
      },
      {
        "anomaly_id": "m240_rank13_loc10690",
        "overlap_with_seizure": false,
        "overlap_sample_start": null,
        "overlap_sample_end": null,
        "overlap_ratio": 0.0,
        "distance_to_onset": null,
        "classification": "false_positive"
      },
      {
        "anomaly_id": "m240_rank14_loc25963",
        "overlap_with_seizure": false,
        "overlap_sample_start": null,
        "overlap_sample_end": null,
        "overlap_ratio": 0.0,
        "distance_to_onset": null,
        "classification": "false_positive"
      },
      {
        "anomaly_id": "m240_rank15_loc26031",
        "overlap_with_seizure": false,
        "overlap_sample_start": null,
        "overlap_sample_end": null,
        "overlap_ratio": 0.0,
        "distance_to_onset": null,
        "classification": "false_positive"
      },
      {
        "anomaly_id": "m800_rank16_loc9299",
        "overlap_with_seizure": false,
        "overlap_sample_start": null,
        "overlap_sample_end": null,
        "overlap_ratio": 0.0,
        "distance_to_onset": null,
        "classification": "false_positive"
      },
      {
        "anomaly_id": "m720_rank17_loc9400",
        "overlap_with_seizure": false,
        "overlap_sample_start": null,
        "overlap_sample_end": null,
        "overlap_ratio": 0.0,
        "distance_to_onset": null,
        "classification": "false_positive"
      },
      {
        "anomaly_id": "m720_rank18_loc9147",
        "overlap_with_seizure": false,
        "overlap_sample_start": null,
        "overlap_sample_end": null,
        "overlap_ratio": 0.0,
        "distance_to_onset": null,
        "classification": "false_positive"
      },
      {
        "anomaly_id": "m560_rank19_loc9127",
        "overlap_with_seizure": false,
        "overlap_sample_start": null,
        "overlap_sample_end": null,
        "overlap_ratio": 0.0,
        "distance_to_onset": null,
        "classification": "false_positive"
      },
      {
        "anomaly_id": "m640_rank20_loc9688",
        "overlap_with_seizure": false,
        "overlap_sample_start": null,
        "overlap_sample_end": null,
        "overlap_ratio": 0.0,
        "distance_to_onset": null,
        "classification": "false_positive"
      },
      {
        "anomaly_id": "m560_rank21_loc10595",
        "overlap_with_seizure": false,
        "overlap_sample_start": null,
        "overlap_sample_end": null,
        "overlap_ratio": 0.0,
        "distance_to_onset": null,
        "classification": "false_positive"
      },
      {
        "anomaly_id": "m640_rank22_loc9528",
        "overlap_with_seizure": false,
        "overlap_sample_start": null,
        "overlap_sample_end": null,
        "overlap_ratio": 0.0,
        "distance_to_onset": null,
        "classification": "false_positive"
      },
      {
        "anomaly_id": "m320_rank23_loc26015",
        "overlap_with_seizure": false,
        "overlap_sample_start": null,
        "overlap_sample_end": null,
        "overlap_ratio": 0.0,
        "distance_to_onset": null,
        "classification": "false_positive"
      },
      {
        "anomaly_id": "m240_rank24_loc10594",
        "overlap_with_seizure": false,
        "overlap_sample_start": null,
        "overlap_sample_end": null,
        "overlap_ratio": 0.0,
        "distance_to_onset": null,
        "classification": "false_positive"
      },
      {
        "anomaly_id": "m480_rank25_loc9206",
        "overlap_with_seizure": false,
        "overlap_sample_start": null,
        "overlap_sample_end": null,
        "overlap_ratio": 0.0,
        "distance_to_onset": null,
        "classification": "false_positive"
      },
      {
        "anomaly_id": "m560_rank26_loc9688",
        "overlap_with_seizure": false,
        "overlap_sample_start": null,
        "overlap_sample_end": null,
        "overlap_ratio": 0.0,
        "distance_to_onset": null,
        "classification": "false_positive"
      },
      {
        "anomaly_id": "m640_rank27_loc9210",
        "overlap_with_seizure": false,
        "overlap_sample_start": null,
        "overlap_sample_end": null,
        "overlap_ratio": 0.0,
        "distance_to_onset": null,
        "classification": "false_positive"
      },
      {
        "anomaly_id": "m400_rank28_loc25837",
        "overlap_with_seizure": false,
        "overlap_sample_start": null,
        "overlap_sample_end": null,
        "overlap_ratio": 0.0,
        "distance_to_onset": null,
        "classification": "false_positive"
      },
      {
        "anomaly_id": "m560_rank29_loc9530",
        "overlap_with_seizure": false,
        "overlap_sample_start": null,
        "overlap_sample_end": null,
        "overlap_ratio": 0.0,
        "distance_to_onset": null,
        "classification": "false_positive"
      },
      {
        "anomaly_id": "m480_rank30_loc9688",
        "overlap_with_seizure": false,
        "overlap_sample_start": null,
        "overlap_sample_end": null,
        "overlap_ratio": 0.0,
        "distance_to_onset": null,
        "classification": "false_positive"
      },
      {
        "anomaly_id": "m560_rank31_loc9390",
        "overlap_with_seizure": false,
        "overlap_sample_start": null,
        "overlap_sample_end": null,
        "overlap_ratio": 0.0,
        "distance_to_onset": null,
        "classification": "false_positive"
      },
      {
        "anomaly_id": "m160_rank32_loc10720",
        "overlap_with_seizure": false,
        "overlap_sample_start": null,
        "overlap_sample_end": null,
        "overlap_ratio": 0.0,
        "distance_to_onset": null,
        "classification": "false_positive"
      },
      {
        "anomaly_id": "m400_rank33_loc9285",
        "overlap_with_seizure": false,
        "overlap_sample_start": null,
        "overlap_sample_end": null,
        "overlap_ratio": 0.0,
        "distance_to_onset": null,
        "classification": "false_positive"
      },
      {
        "anomaly_id": "m160_rank34_loc26044",
        "overlap_with_seizure": false,
        "overlap_sample_start": null,
        "overlap_sample_end": null,
        "overlap_ratio": 0.0,
        "distance_to_onset": null,
        "classification": "false_positive"
      },
      {
        "anomaly_id": "m480_rank35_loc16610",
        "overlap_with_seizure": false,
        "overlap_sample_start": null,
        "overlap_sample_end": null,
        "overlap_ratio": 0.0,
        "distance_to_onset": null,
        "classification": "false_positive"
      },
      {
        "anomaly_id": "m800_rank36_loc10583",
        "overlap_with_seizure": false,
        "overlap_sample_start": null,
        "overlap_sample_end": null,
        "overlap_ratio": 0.0,
        "distance_to_onset": null,
        "classification": "false_positive"
      },
      {
        "anomaly_id": "m400_rank37_loc9688",
        "overlap_with_seizure": false,
        "overlap_sample_start": null,
        "overlap_sample_end": null,
        "overlap_ratio": 0.0,
        "distance_to_onset": null,
        "classification": "false_positive"
      },
      {
        "anomaly_id": "m160_rank38_loc25988",
        "overlap_with_seizure": false,
        "overlap_sample_start": null,
        "overlap_sample_end": null,
        "overlap_ratio": 0.0,
        "distance_to_onset": null,
        "classification": "false_positive"
      },
      {
        "anomaly_id": "m320_rank39_loc10684",
        "overlap_with_seizure": false,
        "overlap_sample_start": null,
        "overlap_sample_end": null,
        "overlap_ratio": 0.0,
        "distance_to_onset": null,
        "classification": "false_positive"
      },
      {
        "anomaly_id": "m720_rank40_loc10582",
        "overlap_with_seizure": false,
        "overlap_sample_start": null,
        "overlap_sample_end": null,
        "overlap_ratio": 0.0,
        "distance_to_onset": null,
        "classification": "false_positive"
      },
      {
        "anomaly_id": "m320_rank41_loc9688",
        "overlap_with_seizure": false,
        "overlap_sample_start": null,
        "overlap_sample_end": null,
        "overlap_ratio": 0.0,
        "distance_to_onset": null,
        "classification": "false_positive"
      },
      {
        "anomaly_id": "m160_rank42_loc10594",
        "overlap_with_seizure": false,
        "overlap_sample_start": null,
        "overlap_sample_end": null,
        "overlap_ratio": 0.0,
        "distance_to_onset": null,
        "classification": "false_positive"
      },
      {
        "anomaly_id": "m240_rank43_loc9688",
        "overlap_with_seizure": false,
        "overlap_sample_start": null,
        "overlap_sample_end": null,
        "overlap_ratio": 0.0,
        "distance_to_onset": null,
        "classification": "false_positive"
      },
      {
        "anomaly_id": "m160_rank44_loc10775",
        "overlap_with_seizure": false,
        "overlap_sample_start": null,
        "overlap_sample_end": null,
        "overlap_ratio": 0.0,
        "distance_to_onset": null,
        "classification": "false_positive"
      },
      {
        "anomaly_id": "m80_rank45_loc10782",
        "overlap_with_seizure": false,
        "overlap_sample_start": null,
        "overlap_sample_end": null,
        "overlap_ratio": 0.0,
        "distance_to_onset": null,
        "classification": "false_positive"
      },
      {
        "anomaly_id": "m640_rank46_loc10595",
        "overlap_with_seizure": false,
        "overlap_sample_start": null,
        "overlap_sample_end": null,
        "overlap_ratio": 0.0,
        "distance_to_onset": null,
        "classification": "false_positive"
      },
      {
        "anomaly_id": "m80_rank47_loc26052",
        "overlap_with_seizure": false,
        "overlap_sample_start": null,
        "overlap_sample_end": null,
        "overlap_ratio": 0.0,
        "distance_to_onset": null,
        "classification": "false_positive"
      },
      {
        "anomaly_id": "m80_rank48_loc19684",
        "overlap_with_seizure": false,
        "overlap_sample_start": null,
        "overlap_sample_end": null,
        "overlap_ratio": 0.0,
        "distance_to_onset": null,
        "classification": "false_positive"
      },
      {
        "anomaly_id": "m80_rank49_loc22785",
        "overlap_with_seizure": false,
        "overlap_sample_start": null,
        "overlap_sample_end": null,
        "overlap_ratio": 0.0,
        "distance_to_onset": null,
        "classification": "false_positive"
      },
      {
        "anomaly_id": "m80_rank50_loc18444",
        "overlap_with_seizure": false,
        "overlap_sample_start": null,
        "overlap_sample_end": null,
        "overlap_ratio": 0.0,
        "distance_to_onset": null,
        "classification": "false_positive"
      }
    ]
  }
}